<?xml version='1.0' encoding='utf-8'?>
<!DOCTYPE hibernate-mapping PUBLIC
    "-//Hibernate/Hibernate Mapping DTD 3.0//EN"
    "http://www.hibernate.org/dtd/hibernate-mapping-3.0.dtd">
<hibernate-mapping>

    <class name="edu.umg.DTO.EstudiantesDTO" table="estudiantes" schema="public" catalog="dbProyectoFinal">
        <id name="idEstudiante">
            <column name="id_estudiante" sql-type="integer"/>
        </id>
        <property name="nombre">
            <column name="nombre" sql-type="varchar(255)"/>
        </property>
        <property name="apellido">
            <column name="apellido" sql-type="varchar(255)"/>
        </property>
        <property name="email">
            <column name="email" sql-type="varchar(255)"/>
        </property>
    </class>
</hibernate-mapping>